tranception_pytorch/__init__.py
tranception_pytorch/data.py
tranception_pytorch/train.py
tranception_pytorch/tranception_pytorch.py
tranception_pytorch/util.py
tranception_pytorch_dohlee-0.0.5.dist-info/METADATA
tranception_pytorch_dohlee-0.0.5.dist-info/WHEEL
tranception_pytorch_dohlee-0.0.5.dist-info/top_level.txt
tranception_pytorch_dohlee-0.0.5.dist-info/RECORD
