Metadata-Version: 2.1
Name: tranception-pytorch-dohlee
Version: 0.0.5
Summary: Tranception - Pytorch
Home-page: https://github.com/dohlee/tranception-pytorch
Author: Dohoon Lee
Author-email: dohlee.bioinfo@gmail.com
License: MIT
Keywords: artificial intelligence,genomics,variant effect prediction,protein fitness
Classifier: Development Status :: 4 - Beta
Classifier: Intended Audience :: Developers
Classifier: Topic :: Scientific/Engineering :: Artificial Intelligence
Classifier: License :: OSI Approved :: MIT License
Classifier: Programming Language :: Python :: 3.9
Requires-Dist: einops (>=0.3)
Requires-Dist: numpy
Requires-Dist: torch (>=1.6)
